[
{"series_id": 28, "id": 1, "link": "6933-a28_001", "mp3": "a28/001.mp3", "youtube": "PWOIKaZIcZg", "teacher": "\u6b63\u5149\u8001\u5e2b", "album_id": "a28", "v_mp3_url": "https://audio.zhengjue.net.cn/a28/001.mp3", "v_video_url": "https://video.zhengjue.net.cn/sv/1c07030f-19424da3338/1c07030f-19424da3338.mp4", "name": "\u5b89\u6a02\u884c\u54c1(\u4e00)"},
{"series_id": 28, "id": 2, "link": "6942-a28_002", "mp3": "a28/002.mp3", "youtube": "y1OiLKELt4k", "teacher": "\u6b63\u5149\u8001\u5e2b", "album_id": "a28", "v_mp3_url": "", "v_video_url": "", "name": "\u5b89\u6a02\u884c\u54c1(\u4e8c)"}
]